README.md
setup.py
conda_suggest/__init__.py
conda_suggest/find.py
conda_suggest/generate.py
conda_suggest/main.py
conda_suggest.egg-info/PKG-INFO
conda_suggest.egg-info/SOURCES.txt
conda_suggest.egg-info/dependency_links.txt
conda_suggest.egg-info/entry_points.txt
conda_suggest.egg-info/top_level.txt