Metadata-Version: 2.1
Name: conda-suggest
Version: 0.1.0
Summary: Conda Suggest
Home-page: https://github.com/conda-incubator/conda-suggest
Author: Anthony Scopatz
License: BSD
Platform: UNKNOWN
Classifier: Programming Language :: Python :: 3
Classifier: License :: OSI Approved :: BSD License
Classifier: Operating System :: OS Independent
Requires-Python: >=3.6
